plone.all_in_one_accessibility-2.0.0-py3.11-nspkg.pth
plone/all_in_one_accessibility/__init__.py
plone/all_in_one_accessibility/configure.zcml
plone/all_in_one_accessibility/interfaces.py
plone/all_in_one_accessibility/permissions.zcml
plone/all_in_one_accessibility/setuphandlers.py
plone/all_in_one_accessibility/subscribers.py
plone/all_in_one_accessibility/subscribers.zcml
plone/all_in_one_accessibility/testing.py
plone/all_in_one_accessibility/api/__init__.py
plone/all_in_one_accessibility/api/configure.zcml
plone/all_in_one_accessibility/api/services/__init__.py
plone/all_in_one_accessibility/api/services/configure.zcml
plone/all_in_one_accessibility/api/services/widget/__init__.py
plone/all_in_one_accessibility/api/services/widget/configure.zcml
plone/all_in_one_accessibility/api/services/widget/get.py
plone/all_in_one_accessibility/browser/__init__.py
plone/all_in_one_accessibility/browser/all_in_one_accessibility_add.py
plone/all_in_one_accessibility/browser/all_in_one_accessibility_setting_view.py
plone/all_in_one_accessibility/browser/configure.zcml
plone/all_in_one_accessibility/browser/redirect_edit_view.py
plone/all_in_one_accessibility/browser/viewlets.py
plone/all_in_one_accessibility/browser/viewlets.zcml
plone/all_in_one_accessibility/browser/overrides/.gitkeep
plone/all_in_one_accessibility/browser/static/.gitkeep
plone/all_in_one_accessibility/browser/static/custom.css
plone/all_in_one_accessibility/browser/static/custom.js
plone/all_in_one_accessibility/browser/templates/all_in_one_accessibility_setting_view.pt
plone/all_in_one_accessibility/content/__init__.py
plone/all_in_one_accessibility/content/all_in_one_accessibility_setting.py
plone/all_in_one_accessibility/content/all_in_one_accessibility_setting.xml
plone/all_in_one_accessibility/locales/README.rst
plone/all_in_one_accessibility/locales/__init__.py
plone/all_in_one_accessibility/locales/plone.all_in_one_accessibility.pot
plone/all_in_one_accessibility/locales/update.py
plone_all_in_one_accessibility-2.0.0.dist-info/METADATA
plone_all_in_one_accessibility-2.0.0.dist-info/WHEEL
plone_all_in_one_accessibility-2.0.0.dist-info/entry_points.txt
plone_all_in_one_accessibility-2.0.0.dist-info/namespace_packages.txt
plone_all_in_one_accessibility-2.0.0.dist-info/top_level.txt
plone_all_in_one_accessibility-2.0.0.dist-info/RECORD
