Metadata-Version: 2.4
Name: plone.all_in_one_accessibility
Version: 2.0.0
Summary: An add-on for Plone
Author: Skynet Technologies USA LLC
Author-email: developer3@skynettechnologies.com
License: GPL version 2
Keywords: Python Plone CMS
Classifier: Environment :: Web Environment
Classifier: Framework :: Plone
Classifier: Framework :: Plone :: Addon
Classifier: Framework :: Plone :: 6.0
Classifier: Programming Language :: Python
Classifier: Programming Language :: Python :: 3.11
Classifier: Operating System :: OS Independent
Classifier: License :: OSI Approved :: GNU General Public License v2 (GPLv2)
Requires-Python: >=3.11, <3.12
Requires-Dist: setuptools
Requires-Dist: z3c.jbot
Requires-Dist: plone.api
Requires-Dist: plone.app.dexterity
Provides-Extra: test
Requires-Dist: plone.app.testing; extra == "test"
Requires-Dist: plone.testing>=5.0.0; extra == "test"
Requires-Dist: plone.app.contenttypes; extra == "test"
Requires-Dist: plone.app.robotframework[debug]; extra == "test"
Dynamic: author
Dynamic: author-email
Dynamic: classifier
Dynamic: description
Dynamic: description-content-type
Dynamic: keywords
Dynamic: license
Dynamic: provides-extra
Dynamic: requires-dist
Dynamic: requires-python
Dynamic: summary
